mkenv/__init__.py
mkenv/_version.py
mkenv/common.py
mkenv/converge.py
mkenv/find.py
mkenv/make.py
mkenv/remove.py
mkenv/tests/__init__.py
mkenv/tests/test_common.py
mkenv/tests/test_converge.py
mkenv/tests/test_find.py
mkenv/tests/test_make.py
mkenv/tests/test_remove.py
mkenv/tests/utils.py
mkenv-3.4.0.dist-info/METADATA
mkenv-3.4.0.dist-info/RECORD
mkenv-3.4.0.dist-info/WHEEL
mkenv-3.4.0.dist-info/entry_points.txt
mkenv-3.4.0.dist-info/top_level.txt
