Metadata-Version: 2.1
Name: mkenv
Version: 3.4.0
Summary: A simpler tool for creating venvs in a central location
Home-page: https://github.com/Julian/mkenv
Author: Julian Berman
Author-email: Julian@GrayVines.com
License: MIT
Platform: UNKNOWN
Classifier: Development Status :: 3 - Alpha
Classifier: License :: OSI Approved :: MIT License
Classifier: Operating System :: OS Independent
Classifier: Programming Language :: Python
Classifier: Programming Language :: Python :: 2.7
Classifier: Programming Language :: Python :: 2
Classifier: Programming Language :: Python :: 3.4
Classifier: Programming Language :: Python :: 3.5
Classifier: Programming Language :: Python :: 3.6
Classifier: Programming Language :: Python :: 3
Classifier: Programming Language :: Python :: Implementation :: CPython
Classifier: Programming Language :: Python :: Implementation :: PyPy
Requires-Dist: appdirs
Requires-Dist: attrs
Requires-Dist: click
Requires-Dist: filesystems
Requires-Dist: packaging
Requires-Dist: pytoml (>=0.1.16)
Requires-Dist: tqdm
Requires-Dist: virtualenv
